quinn/__init__.py
quinn/append_if_schema_identical.py
quinn/dataframe_helpers.py
quinn/dataframe_validator.py
quinn/extensions/__init__.py
quinn/extensions/dataframe_ext.py
quinn/extensions/spark_session_ext.py
quinn/functions.py
quinn/math.py
quinn/schema_helpers.py
quinn/split_columns.py
quinn/transformations.py
quinn-0.10.2.dist-info/METADATA
quinn-0.10.2.dist-info/WHEEL
quinn-0.10.2.dist-info/RECORD
