Metadata-Version: 2.1
Name: quinn
Version: 0.10.2
Summary: Pyspark helper methods to maximize developer efficiency
Home-page: https://github.com/MrPowers/quinn/
License: Apache-2.0
Keywords: apachespark,spark,pyspark
Author: MrPowers
Author-email: matthewkevinpowers@gmail.com
Requires-Python: >=3.7,<4.0
Classifier: License :: OSI Approved :: Apache Software License
Classifier: Programming Language :: Python :: 3
Classifier: Programming Language :: Python :: 3.7
Classifier: Programming Language :: Python :: 3.8
Classifier: Programming Language :: Python :: 3.9
Classifier: Programming Language :: Python :: 3.10
Classifier: Programming Language :: Python :: 3.11
